topsis_vishwas_102303170/__init__.py
topsis_vishwas_102303170/topsis.py
topsis_vishwaskhattar_102303170-1.0.1.dist-info/licenses/LICENSE
topsis_vishwaskhattar_102303170-1.0.1.dist-info/METADATA
topsis_vishwaskhattar_102303170-1.0.1.dist-info/WHEEL
topsis_vishwaskhattar_102303170-1.0.1.dist-info/entry_points.txt
topsis_vishwaskhattar_102303170-1.0.1.dist-info/top_level.txt
topsis_vishwaskhattar_102303170-1.0.1.dist-info/RECORD
