Metadata-Version: 2.4
Name: Topsis-VishwasKhattar-102303170
Version: 1.0.1
Summary: A command-line implementation of TOPSIS
Author: Vishwas Khattar
Author-email: your_email@gmail.com
License-File: LICENSE
Requires-Dist: pandas
Requires-Dist: numpy
Dynamic: author
Dynamic: author-email
Dynamic: description
Dynamic: description-content-type
Dynamic: license-file
Dynamic: requires-dist
Dynamic: summary
